david_home_automation/__init__.py
david_home_automation/config.py
david_home_automation/main.py
david_home_automation/server.py
david_home_automation/static/index.html
david_home_automation/static/script.js
david_home_automation/static/style.css
david_home_automation/utils.py
david_home_automation-0.1.38.dist-info/WHEEL
david_home_automation-0.1.38.dist-info/METADATA
david_home_automation-0.1.38.dist-info/RECORD
