Metadata-Version: 2.1
Name: david-home-automation
Version: 0.1.38
Summary: 
Author: David Gengenbach
Author-email: info@davidgengenbach.de
Requires-Python: >=3.7,<4.0
Classifier: Programming Language :: Python :: 3
Classifier: Programming Language :: Python :: 3.7
Classifier: Programming Language :: Python :: 3.8
Requires-Dist: Flask (>=2.0.2,<3.0.0)
Requires-Dist: click (>=8.0.0,<9.0.0)
Requires-Dist: pyyaml (>=5.0,<6.0)
Requires-Dist: wakeonlan (>=2.0.1,<3.0.0)
